[
  {
    "id": "inside-out-2026-09-05-1630",
    "company": "Hamburg Ballett",
    "city": "Hamburg",
    "venue": "Staatsoper, opera stabile",
    "title": "Inside Out",
    "date": "2026-09-05",
    "time": "16:30",
    "datetime": "2026-09-05T16:30:00",
    "ticketUrl": null,
    "officialUrl": "https://hamburgballett.die-hamburgische-staatsoper.de/de/programm/ballett/3141-inside-out"
  },
  {
    "id": "theaternacht-hamburg-2026-09-05-1800",
    "company": "Hamburg Ballett",
    "city": "Hamburg",
    "venue": "Staatsoper, Großes Haus",
    "title": "Theaternacht Hamburg",
    "date": "2026-09-05",
    "time": "18:00",
    "datetime": "2026-09-05T18:00:00",
    "ticketUrl": null,
    "officialUrl": "https://hamburgballett.die-hamburgische-staatsoper.de/de/programm/details/2147484977-theaternacht-hamburg"
  },
  {
    "id": "patenklassen-ballett-a-cinderella-story-2026-09-10-0930",
    "company": "Hamburg Ballett",
    "city": "Hamburg",
    "venue": "Staatsoper, Großes Haus",
    "title": "Patenklassen Ballett – A Cinderella Story",
    "date": "2026-09-10",
    "time": "09:30",
    "datetime": "2026-09-10T09:30:00",
    "ticketUrl": null,
    "officialUrl": "https://hamburgballett.die-hamburgische-staatsoper.de/de/programm/ballett/3050-patenklassen-ballett"
  },
  {
    "id": "balletttester-innen-a-cinderella-story-2026-09-11-1700",
    "company": "Hamburg Ballett",
    "city": "Hamburg",
    "venue": "Staatsoper, Großes Haus",
    "title": "BallettTester:innen – A Cinderella Story",
    "date": "2026-09-11",
    "time": "17:00",
    "datetime": "2026-09-11T17:00:00",
    "ticketUrl": null,
    "officialUrl": "https://hamburgballett.die-hamburgische-staatsoper.de/de/programm/ballett/3053-balletttester-innen"
  },
  {
    "id": "a-cinderella-story-2026-09-13-1800",
    "company": "Hamburg Ballett",
    "city": "Hamburg",
    "venue": "Staatsoper, Großes Haus",
    "title": "A Cinderella Story",
    "date": "2026-09-13",
    "time": "18:00",
    "datetime": "2026-09-13T18:00:00",
    "ticketUrl": "https://webshop.staatsoper-hamburg.de/webshop/webticket/shop?event=11072",
    "officialUrl": "https://hamburgballett.die-hamburgische-staatsoper.de/de/programm/ballett/319-a-cinderella-story"
  },
  {
    "id": "a-cinderella-story-2026-09-15-1930",
    "company": "Hamburg Ballett",
    "city": "Hamburg",
    "venue": "Staatsoper, Großes Haus",
    "title": "A Cinderella Story",
    "date": "2026-09-15",
    "time": "19:30",
    "datetime": "2026-09-15T19:30:00",
    "ticketUrl": "https://webshop.staatsoper-hamburg.de/webshop/webticket/shop?event=11078",
    "officialUrl": "https://hamburgballett.die-hamburgische-staatsoper.de/de/programm/ballett/319-a-cinderella-story"
  },
  {
    "id": "a-cinderella-story-2026-09-17-1930",
    "company": "Hamburg Ballett",
    "city": "Hamburg",
    "venue": "Staatsoper, Großes Haus",
    "title": "A Cinderella Story",
    "date": "2026-09-17",
    "time": "19:30",
    "datetime": "2026-09-17T19:30:00",
    "ticketUrl": "https://webshop.staatsoper-hamburg.de/webshop/webticket/shop?event=11073",
    "officialUrl": "https://hamburgballett.die-hamburgische-staatsoper.de/de/programm/ballett/319-a-cinderella-story"
  },
  {
    "id": "a-cinderella-story-2026-09-18-1930",
    "company": "Hamburg Ballett",
    "city": "Hamburg",
    "venue": "Staatsoper, Großes Haus",
    "title": "A Cinderella Story",
    "date": "2026-09-18",
    "time": "19:30",
    "datetime": "2026-09-18T19:30:00",
    "ticketUrl": "https://webshop.staatsoper-hamburg.de/webshop/webticket/shop?event=11074",
    "officialUrl": "https://hamburgballett.die-hamburgische-staatsoper.de/de/programm/ballett/319-a-cinderella-story"
  },
  {
    "id": "inside-out-2026-09-19-1900",
    "company": "Hamburg Ballett",
    "city": "Hamburg",
    "venue": "Staatsoper, opera stabile",
    "title": "Inside Out",
    "date": "2026-09-19",
    "time": "19:00",
    "datetime": "2026-09-19T19:00:00",
    "ticketUrl": null,
    "officialUrl": "https://hamburgballett.die-hamburgische-staatsoper.de/de/programm/ballett/3141-inside-out"
  },
  {
    "id": "eintauchen-ins-ballettzentrum-2026-09-26-1000",
    "company": "Hamburg Ballett",
    "city": "Hamburg",
    "venue": "Ballettzentrum Hamburg – John Neumeier",
    "title": "Eintauchen ins Ballettzentrum",
    "date": "2026-09-26",
    "time": "10:00",
    "datetime": "2026-09-26T10:00:00",
    "ticketUrl": "https://webshop.staatsoper-hamburg.de/webshop/webticket/shop?event=11350",
    "officialUrl": "https://hamburgballett.die-hamburgische-staatsoper.de/de/programm/ballett/3146-eintauchen-ins-ballettzentrum"
  },
  {
    "id": "tod-in-venedig-2026-09-26-1900",
    "company": "Hamburg Ballett",
    "city": "Hamburg",
    "venue": "Staatsoper, Großes Haus",
    "title": "Tod in Venedig",
    "date": "2026-09-26",
    "time": "19:00",
    "datetime": "2026-09-26T19:00:00",
    "ticketUrl": "https://webshop.staatsoper-hamburg.de/webshop/webticket/shop?event=11273",
    "officialUrl": "https://hamburgballett.die-hamburgische-staatsoper.de/de/programm/ballett/520-tod-in-venedig"
  },
  {
    "id": "tanz-fur-mich-2026-10-01-1900",
    "company": "Hamburg Ballett",
    "city": "Hamburg",
    "venue": "Ballettzentrum Hamburg – John Neumeier",
    "title": "Tanz für mich",
    "date": "2026-10-01",
    "time": "19:00",
    "datetime": "2026-10-01T19:00:00",
    "ticketUrl": null,
    "officialUrl": "https://hamburgballett.die-hamburgische-staatsoper.de/de/programm/ballett/3047-tanz-fuer-mich"
  },
  {
    "id": "ballett-werkstatt-2026-10-01-1900",
    "company": "Hamburg Ballett",
    "city": "Hamburg",
    "venue": "Gastspiel in Baden-Baden, Festspielhaus",
    "title": "Ballett-Werkstatt",
    "date": "2026-10-01",
    "time": "19:00",
    "datetime": "2026-10-01T19:00:00",
    "ticketUrl": null,
    "officialUrl": "https://hamburgballett.die-hamburgische-staatsoper.de/de/programm/ballett/168-ballett-werkstatt"
  },
  {
    "id": "absprung-v-2026-10-05-1800",
    "company": "Hamburg Ballett",
    "city": "Hamburg",
    "venue": "Gastspiel in Baden-Baden, Festspielhaus",
    "title": "Absprung V",
    "date": "2026-10-05",
    "time": "18:00",
    "datetime": "2026-10-05T18:00:00",
    "ticketUrl": null,
    "officialUrl": "https://hamburgballett.die-hamburgische-staatsoper.de/de/programm/ballett/2147484845-absprung-v"
  },
  {
    "id": "bundesjugendballett-2026-10-06-1900",
    "company": "Hamburg Ballett",
    "city": "Hamburg",
    "venue": "Gastspiel in Baden-Baden, Festspielhaus",
    "title": "Bundesjugendballett",
    "date": "2026-10-06",
    "time": "19:00",
    "datetime": "2026-10-06T19:00:00",
    "ticketUrl": null,
    "officialUrl": "https://hamburgballett.die-hamburgische-staatsoper.de/de/programm/ballett/742-bundesjugendballett"
  },
  {
    "id": "bundesjugendballett-2026-10-07-1900",
    "company": "Hamburg Ballett",
    "city": "Hamburg",
    "venue": "Gastspiel in Baden-Baden, Festspielhaus",
    "title": "Bundesjugendballett",
    "date": "2026-10-07",
    "time": "19:00",
    "datetime": "2026-10-07T19:00:00",
    "ticketUrl": null,
    "officialUrl": "https://hamburgballett.die-hamburgische-staatsoper.de/de/programm/ballett/742-bundesjugendballett"
  },
  {
    "id": "der-nussknacker-2026-10-09-1930",
    "company": "Hamburg Ballett",
    "city": "Hamburg",
    "venue": "Gastspiel in Baden-Baden, Festspielhaus",
    "title": "Der Nussknacker",
    "date": "2026-10-09",
    "time": "19:30",
    "datetime": "2026-10-09T19:30:00",
    "ticketUrl": null,
    "officialUrl": "https://hamburgballett.die-hamburgische-staatsoper.de/de/programm/ballett/201-der-nussknacker"
  },
  {
    "id": "der-nussknacker-2026-10-10-1930",
    "company": "Hamburg Ballett",
    "city": "Hamburg",
    "venue": "Gastspiel in Baden-Baden, Festspielhaus",
    "title": "Der Nussknacker",
    "date": "2026-10-10",
    "time": "19:30",
    "datetime": "2026-10-10T19:30:00",
    "ticketUrl": null,
    "officialUrl": "https://hamburgballett.die-hamburgische-staatsoper.de/de/programm/ballett/201-der-nussknacker"
  },
  {
    "id": "der-nussknacker-2026-10-11-1500",
    "company": "Hamburg Ballett",
    "city": "Hamburg",
    "venue": "Gastspiel in Baden-Baden, Festspielhaus",
    "title": "Der Nussknacker",
    "date": "2026-10-11",
    "time": "15:00",
    "datetime": "2026-10-11T15:00:00",
    "ticketUrl": null,
    "officialUrl": "https://hamburgballett.die-hamburgische-staatsoper.de/de/programm/ballett/201-der-nussknacker"
  },
  {
    "id": "a-cinderella-story-2026-10-14-1930",
    "company": "Hamburg Ballett",
    "city": "Hamburg",
    "venue": "Staatsoper, Großes Haus",
    "title": "A Cinderella Story",
    "date": "2026-10-14",
    "time": "19:30",
    "datetime": "2026-10-14T19:30:00",
    "ticketUrl": "https://webshop.staatsoper-hamburg.de/webshop/webticket/shop?event=11075",
    "officialUrl": "https://hamburgballett.die-hamburgische-staatsoper.de/de/programm/ballett/319-a-cinderella-story"
  },
  {
    "id": "a-cinderella-story-2026-10-15-1930",
    "company": "Hamburg Ballett",
    "city": "Hamburg",
    "venue": "Staatsoper, Großes Haus",
    "title": "A Cinderella Story",
    "date": "2026-10-15",
    "time": "19:30",
    "datetime": "2026-10-15T19:30:00",
    "ticketUrl": "https://webshop.staatsoper-hamburg.de/webshop/webticket/shop?event=11076",
    "officialUrl": "https://hamburgballett.die-hamburgische-staatsoper.de/de/programm/ballett/319-a-cinderella-story"
  },
  {
    "id": "a-cinderella-story-2026-10-16-1930",
    "company": "Hamburg Ballett",
    "city": "Hamburg",
    "venue": "Staatsoper, Großes Haus",
    "title": "A Cinderella Story",
    "date": "2026-10-16",
    "time": "19:30",
    "datetime": "2026-10-16T19:30:00",
    "ticketUrl": "https://webshop.staatsoper-hamburg.de/webshop/webticket/shop?event=11077",
    "officialUrl": "https://hamburgballett.die-hamburgische-staatsoper.de/de/programm/ballett/319-a-cinderella-story"
  },
  {
    "id": "die-kameliendame-2026-10-21-1900",
    "company": "Hamburg Ballett",
    "city": "Hamburg",
    "venue": "Staatsoper, Großes Haus",
    "title": "Die Kameliendame",
    "date": "2026-10-21",
    "time": "19:00",
    "datetime": "2026-10-21T19:00:00",
    "ticketUrl": "https://webshop.staatsoper-hamburg.de/webshop/webticket/shop?event=11113",
    "officialUrl": "https://hamburgballett.die-hamburgische-staatsoper.de/de/programm/ballett/329-die-kameliendame"
  },
  {
    "id": "tanz-fur-mich-2026-10-22-1900",
    "company": "Hamburg Ballett",
    "city": "Hamburg",
    "venue": "Ballettzentrum Hamburg – John Neumeier",
    "title": "Tanz für mich",
    "date": "2026-10-22",
    "time": "19:00",
    "datetime": "2026-10-22T19:00:00",
    "ticketUrl": null,
    "officialUrl": "https://hamburgballett.die-hamburgische-staatsoper.de/de/programm/ballett/3048-tanz-fuer-mich"
  },
  {
    "id": "die-kameliendame-2026-10-23-1900",
    "company": "Hamburg Ballett",
    "city": "Hamburg",
    "venue": "Staatsoper, Großes Haus",
    "title": "Die Kameliendame",
    "date": "2026-10-23",
    "time": "19:00",
    "datetime": "2026-10-23T19:00:00",
    "ticketUrl": "https://webshop.staatsoper-hamburg.de/webshop/webticket/shop?event=11121",
    "officialUrl": "https://hamburgballett.die-hamburgische-staatsoper.de/de/programm/ballett/329-die-kameliendame"
  },
  {
    "id": "die-kameliendame-2026-10-24-1900",
    "company": "Hamburg Ballett",
    "city": "Hamburg",
    "venue": "Staatsoper, Großes Haus",
    "title": "Die Kameliendame",
    "date": "2026-10-24",
    "time": "19:00",
    "datetime": "2026-10-24T19:00:00",
    "ticketUrl": "https://webshop.staatsoper-hamburg.de/webshop/webticket/shop?event=11118",
    "officialUrl": "https://hamburgballett.die-hamburgische-staatsoper.de/de/programm/ballett/329-die-kameliendame"
  },
  {
    "id": "ballett-werkstatt-2026-10-25-1100",
    "company": "Hamburg Ballett",
    "city": "Hamburg",
    "venue": "Staatsoper, Großes Haus",
    "title": "Ballett-Werkstatt",
    "date": "2026-10-25",
    "time": "11:00",
    "datetime": "2026-10-25T11:00:00",
    "ticketUrl": "https://webshop.staatsoper-hamburg.de/webshop/webticket/shop?event=11283",
    "officialUrl": "https://hamburgballett.die-hamburgische-staatsoper.de/de/programm/ballett/168-ballett-werkstatt"
  },
  {
    "id": "die-kameliendame-2026-10-25-1630",
    "company": "Hamburg Ballett",
    "city": "Hamburg",
    "venue": "Staatsoper, Großes Haus",
    "title": "Die Kameliendame",
    "date": "2026-10-25",
    "time": "16:30",
    "datetime": "2026-10-25T16:30:00",
    "ticketUrl": "https://webshop.staatsoper-hamburg.de/webshop/webticket/shop?event=11119",
    "officialUrl": "https://hamburgballett.die-hamburgische-staatsoper.de/de/programm/ballett/329-die-kameliendame"
  },
  {
    "id": "die-kameliendame-2026-10-28-1900",
    "company": "Hamburg Ballett",
    "city": "Hamburg",
    "venue": "Staatsoper, Großes Haus",
    "title": "Die Kameliendame",
    "date": "2026-10-28",
    "time": "19:00",
    "datetime": "2026-10-28T19:00:00",
    "ticketUrl": "https://webshop.staatsoper-hamburg.de/webshop/webticket/shop?event=11120",
    "officialUrl": "https://hamburgballett.die-hamburgische-staatsoper.de/de/programm/ballett/329-die-kameliendame"
  },
  {
    "id": "wunderland-2026-10-30-1930",
    "company": "Hamburg Ballett",
    "city": "Hamburg",
    "venue": "Staatsoper, Großes Haus",
    "title": "Wunderland",
    "date": "2026-10-30",
    "time": "19:30",
    "datetime": "2026-10-30T19:30:00",
    "ticketUrl": "https://webshop.staatsoper-hamburg.de/webshop/webticket/shop?event=11209",
    "officialUrl": "https://hamburgballett.die-hamburgische-staatsoper.de/de/programm/ballett/1911-wunderland"
  },
  {
    "id": "wunderland-2026-10-31-1800",
    "company": "Hamburg Ballett",
    "city": "Hamburg",
    "venue": "Staatsoper, Großes Haus",
    "title": "Wunderland",
    "date": "2026-10-31",
    "time": "18:00",
    "datetime": "2026-10-31T18:00:00",
    "ticketUrl": "https://webshop.staatsoper-hamburg.de/webshop/webticket/shop?event=11217",
    "officialUrl": "https://hamburgballett.die-hamburgische-staatsoper.de/de/programm/ballett/1911-wunderland"
  },
  {
    "id": "tanz-fur-mich-2026-11-05-1900",
    "company": "Hamburg Ballett",
    "city": "Hamburg",
    "venue": "Ballettzentrum Hamburg – John Neumeier",
    "title": "Tanz für mich",
    "date": "2026-11-05",
    "time": "19:00",
    "datetime": "2026-11-05T19:00:00",
    "ticketUrl": null,
    "officialUrl": "https://hamburgballett.die-hamburgische-staatsoper.de/de/programm/ballett/3047-tanz-fuer-mich"
  },
  {
    "id": "wunderland-2026-11-06-1930",
    "company": "Hamburg Ballett",
    "city": "Hamburg",
    "venue": "Staatsoper, Großes Haus",
    "title": "Wunderland",
    "date": "2026-11-06",
    "time": "19:30",
    "datetime": "2026-11-06T19:30:00",
    "ticketUrl": "https://webshop.staatsoper-hamburg.de/webshop/webticket/shop?event=11210",
    "officialUrl": "https://hamburgballett.die-hamburgische-staatsoper.de/de/programm/ballett/1911-wunderland"
  },
  {
    "id": "wunderland-2026-11-10-1930",
    "company": "Hamburg Ballett",
    "city": "Hamburg",
    "venue": "Staatsoper, Großes Haus",
    "title": "Wunderland",
    "date": "2026-11-10",
    "time": "19:30",
    "datetime": "2026-11-10T19:30:00",
    "ticketUrl": "https://webshop.staatsoper-hamburg.de/webshop/webticket/shop?event=11211",
    "officialUrl": "https://hamburgballett.die-hamburgische-staatsoper.de/de/programm/ballett/1911-wunderland"
  },
  {
    "id": "ballettinsider-innen-wunderland-2026-11-12-1845",
    "company": "Hamburg Ballett",
    "city": "Hamburg",
    "venue": "Staatsoper, Gästezimmer",
    "title": "BallettInsider:innen – Wunderland",
    "date": "2026-11-12",
    "time": "18:45",
    "datetime": "2026-11-12T18:45:00",
    "ticketUrl": null,
    "officialUrl": "https://hamburgballett.die-hamburgische-staatsoper.de/de/programm/ballett/3054-ballettinsider-innen"
  },
  {
    "id": "wunderland-2026-11-12-1930",
    "company": "Hamburg Ballett",
    "city": "Hamburg",
    "venue": "Staatsoper, Großes Haus",
    "title": "Wunderland",
    "date": "2026-11-12",
    "time": "19:30",
    "datetime": "2026-11-12T19:30:00",
    "ticketUrl": "https://webshop.staatsoper-hamburg.de/webshop/webticket/shop?event=11212",
    "officialUrl": "https://hamburgballett.die-hamburgische-staatsoper.de/de/programm/ballett/1911-wunderland"
  },
  {
    "id": "wunderland-2026-11-13-1930",
    "company": "Hamburg Ballett",
    "city": "Hamburg",
    "venue": "Staatsoper, Großes Haus",
    "title": "Wunderland",
    "date": "2026-11-13",
    "time": "19:30",
    "datetime": "2026-11-13T19:30:00",
    "ticketUrl": "https://webshop.staatsoper-hamburg.de/webshop/webticket/shop?event=11213",
    "officialUrl": "https://hamburgballett.die-hamburgische-staatsoper.de/de/programm/ballett/1911-wunderland"
  },
  {
    "id": "eintauchen-ins-ballettzentrum-2026-11-14-1000",
    "company": "Hamburg Ballett",
    "city": "Hamburg",
    "venue": "Ballettzentrum Hamburg – John Neumeier",
    "title": "Eintauchen ins Ballettzentrum",
    "date": "2026-11-14",
    "time": "10:00",
    "datetime": "2026-11-14T10:00:00",
    "ticketUrl": null,
    "officialUrl": "https://hamburgballett.die-hamburgische-staatsoper.de/de/programm/ballett/3146-eintauchen-ins-ballettzentrum"
  },
  {
    "id": "wunderland-2026-11-18-1930",
    "company": "Hamburg Ballett",
    "city": "Hamburg",
    "venue": "Staatsoper, Großes Haus",
    "title": "Wunderland",
    "date": "2026-11-18",
    "time": "19:30",
    "datetime": "2026-11-18T19:30:00",
    "ticketUrl": "https://webshop.staatsoper-hamburg.de/webshop/webticket/shop?event=11214",
    "officialUrl": "https://hamburgballett.die-hamburgische-staatsoper.de/de/programm/ballett/1911-wunderland"
  },
  {
    "id": "patenklassen-ballett-neue-welten-2026-11-20-0930",
    "company": "Hamburg Ballett",
    "city": "Hamburg",
    "venue": "Staatsoper, Großes Haus",
    "title": "Patenklassen Ballett – NEUE WELTEN",
    "date": "2026-11-20",
    "time": "09:30",
    "datetime": "2026-11-20T09:30:00",
    "ticketUrl": null,
    "officialUrl": "https://hamburgballett.die-hamburgische-staatsoper.de/de/programm/ballett/3050-patenklassen-ballett"
  },
  {
    "id": "wunderland-2026-11-21-1930",
    "company": "Hamburg Ballett",
    "city": "Hamburg",
    "venue": "Staatsoper, Großes Haus",
    "title": "Wunderland",
    "date": "2026-11-21",
    "time": "19:30",
    "datetime": "2026-11-21T19:30:00",
    "ticketUrl": "https://webshop.staatsoper-hamburg.de/webshop/webticket/shop?event=11215",
    "officialUrl": "https://hamburgballett.die-hamburgische-staatsoper.de/de/programm/ballett/1911-wunderland"
  },
  {
    "id": "ballett-werkstatt-2026-11-22-1100",
    "company": "Hamburg Ballett",
    "city": "Hamburg",
    "venue": "Staatsoper, Großes Haus",
    "title": "Ballett-Werkstatt",
    "date": "2026-11-22",
    "time": "11:00",
    "datetime": "2026-11-22T11:00:00",
    "ticketUrl": "https://webshop.staatsoper-hamburg.de/webshop/webticket/shop?event=11287",
    "officialUrl": "https://hamburgballett.die-hamburgische-staatsoper.de/de/programm/ballett/168-ballett-werkstatt"
  },
  {
    "id": "sneak-klub-generalprobe-neue-welten-2026-12-04-1700",
    "company": "Hamburg Ballett",
    "city": "Hamburg",
    "venue": "Staatsoper, Großes Haus",
    "title": "Sneak Klub – Generalprobe: NEUE WELTEN",
    "date": "2026-12-04",
    "time": "17:00",
    "datetime": "2026-12-04T17:00:00",
    "ticketUrl": null,
    "officialUrl": "https://hamburgballett.die-hamburgische-staatsoper.de/de/programm/ballett/2147484910-sneak-klub"
  },
  {
    "id": "neue-welten-2026-12-05-1800",
    "company": "Hamburg Ballett",
    "city": "Hamburg",
    "venue": "Staatsoper, Großes Haus",
    "title": "NEUE WELTEN",
    "date": "2026-12-05",
    "time": "18:00",
    "datetime": "2026-12-05T18:00:00",
    "ticketUrl": "https://webshop.staatsoper-hamburg.de/webshop/webticket/shop?event=11154",
    "officialUrl": "https://hamburgballett.die-hamburgische-staatsoper.de/de/programm/ballett/1905-neue-welten"
  },
  {
    "id": "neue-welten-2026-12-09-1930",
    "company": "Hamburg Ballett",
    "city": "Hamburg",
    "venue": "Staatsoper, Großes Haus",
    "title": "NEUE WELTEN",
    "date": "2026-12-09",
    "time": "19:30",
    "datetime": "2026-12-09T19:30:00",
    "ticketUrl": "https://webshop.staatsoper-hamburg.de/webshop/webticket/shop?event=11155",
    "officialUrl": "https://hamburgballett.die-hamburgische-staatsoper.de/de/programm/ballett/1905-neue-welten"
  },
  {
    "id": "tanz-fur-mich-2026-12-10-1900",
    "company": "Hamburg Ballett",
    "city": "Hamburg",
    "venue": "Ballettzentrum Hamburg – John Neumeier",
    "title": "Tanz für mich",
    "date": "2026-12-10",
    "time": "19:00",
    "datetime": "2026-12-10T19:00:00",
    "ticketUrl": null,
    "officialUrl": "https://hamburgballett.die-hamburgische-staatsoper.de/de/programm/ballett/3047-tanz-fuer-mich"
  },
  {
    "id": "neue-welten-2026-12-11-1930",
    "company": "Hamburg Ballett",
    "city": "Hamburg",
    "venue": "Staatsoper, Großes Haus",
    "title": "NEUE WELTEN",
    "date": "2026-12-11",
    "time": "19:30",
    "datetime": "2026-12-11T19:30:00",
    "ticketUrl": "https://webshop.staatsoper-hamburg.de/webshop/webticket/shop?event=11160",
    "officialUrl": "https://hamburgballett.die-hamburgische-staatsoper.de/de/programm/ballett/1905-neue-welten"
  },
  {
    "id": "der-nussknacker-2026-12-16-1930",
    "company": "Hamburg Ballett",
    "city": "Hamburg",
    "venue": "Staatsoper, Großes Haus",
    "title": "Der Nussknacker",
    "date": "2026-12-16",
    "time": "19:30",
    "datetime": "2026-12-16T19:30:00",
    "ticketUrl": "https://webshop.staatsoper-hamburg.de/webshop/webticket/shop?event=11161",
    "officialUrl": "https://hamburgballett.die-hamburgische-staatsoper.de/de/programm/ballett/201-der-nussknacker"
  },
  {
    "id": "tanz-fur-mich-2026-12-17-1900",
    "company": "Hamburg Ballett",
    "city": "Hamburg",
    "venue": "Ballettzentrum Hamburg – John Neumeier",
    "title": "Tanz für mich",
    "date": "2026-12-17",
    "time": "19:00",
    "datetime": "2026-12-17T19:00:00",
    "ticketUrl": null,
    "officialUrl": "https://hamburgballett.die-hamburgische-staatsoper.de/de/programm/ballett/3048-tanz-fuer-mich"
  },
  {
    "id": "der-nussknacker-2026-12-17-1930",
    "company": "Hamburg Ballett",
    "city": "Hamburg",
    "venue": "Staatsoper, Großes Haus",
    "title": "Der Nussknacker",
    "date": "2026-12-17",
    "time": "19:30",
    "datetime": "2026-12-17T19:30:00",
    "ticketUrl": "https://webshop.staatsoper-hamburg.de/webshop/webticket/shop?event=11162",
    "officialUrl": "https://hamburgballett.die-hamburgische-staatsoper.de/de/programm/ballett/201-der-nussknacker"
  },
  {
    "id": "neue-welten-2026-12-19-1930",
    "company": "Hamburg Ballett",
    "city": "Hamburg",
    "venue": "Staatsoper, Großes Haus",
    "title": "NEUE WELTEN",
    "date": "2026-12-19",
    "time": "19:30",
    "datetime": "2026-12-19T19:30:00",
    "ticketUrl": "https://webshop.staatsoper-hamburg.de/webshop/webticket/shop?event=11156",
    "officialUrl": "https://hamburgballett.die-hamburgische-staatsoper.de/de/programm/ballett/1905-neue-welten"
  },
  {
    "id": "der-nussknacker-2026-12-22-1930",
    "company": "Hamburg Ballett",
    "city": "Hamburg",
    "venue": "Staatsoper, Großes Haus",
    "title": "Der Nussknacker",
    "date": "2026-12-22",
    "time": "19:30",
    "datetime": "2026-12-22T19:30:00",
    "ticketUrl": "https://webshop.staatsoper-hamburg.de/webshop/webticket/shop?event=11163",
    "officialUrl": "https://hamburgballett.die-hamburgische-staatsoper.de/de/programm/ballett/201-der-nussknacker"
  },
  {
    "id": "der-nussknacker-2026-12-25-1400",
    "company": "Hamburg Ballett",
    "city": "Hamburg",
    "venue": "Staatsoper, Großes Haus",
    "title": "Der Nussknacker",
    "date": "2026-12-25",
    "time": "14:00",
    "datetime": "2026-12-25T14:00:00",
    "ticketUrl": "https://webshop.staatsoper-hamburg.de/webshop/webticket/shop?event=11164",
    "officialUrl": "https://hamburgballett.die-hamburgische-staatsoper.de/de/programm/ballett/201-der-nussknacker"
  },
  {
    "id": "der-nussknacker-2026-12-25-1900",
    "company": "Hamburg Ballett",
    "city": "Hamburg",
    "venue": "Staatsoper, Großes Haus",
    "title": "Der Nussknacker",
    "date": "2026-12-25",
    "time": "19:00",
    "datetime": "2026-12-25T19:00:00",
    "ticketUrl": "https://webshop.staatsoper-hamburg.de/webshop/webticket/shop?event=11165",
    "officialUrl": "https://hamburgballett.die-hamburgische-staatsoper.de/de/programm/ballett/201-der-nussknacker"
  },
  {
    "id": "der-nussknacker-2026-12-27-1400",
    "company": "Hamburg Ballett",
    "city": "Hamburg",
    "venue": "Staatsoper, Großes Haus",
    "title": "Der Nussknacker",
    "date": "2026-12-27",
    "time": "14:00",
    "datetime": "2026-12-27T14:00:00",
    "ticketUrl": "https://webshop.staatsoper-hamburg.de/webshop/webticket/shop?event=11167",
    "officialUrl": "https://hamburgballett.die-hamburgische-staatsoper.de/de/programm/ballett/201-der-nussknacker"
  },
  {
    "id": "der-nussknacker-2026-12-27-1900",
    "company": "Hamburg Ballett",
    "city": "Hamburg",
    "venue": "Staatsoper, Großes Haus",
    "title": "Der Nussknacker",
    "date": "2026-12-27",
    "time": "19:00",
    "datetime": "2026-12-27T19:00:00",
    "ticketUrl": "https://webshop.staatsoper-hamburg.de/webshop/webticket/shop?event=11166",
    "officialUrl": "https://hamburgballett.die-hamburgische-staatsoper.de/de/programm/ballett/201-der-nussknacker"
  },
  {
    "id": "der-nussknacker-2027-01-01-1800",
    "company": "Hamburg Ballett",
    "city": "Hamburg",
    "venue": "Staatsoper, Großes Haus",
    "title": "Der Nussknacker",
    "date": "2027-01-01",
    "time": "18:00",
    "datetime": "2027-01-01T18:00:00",
    "ticketUrl": "https://webshop.staatsoper-hamburg.de/webshop/webticket/shop?event=11168",
    "officialUrl": "https://hamburgballett.die-hamburgische-staatsoper.de/de/programm/ballett/201-der-nussknacker"
  },
  {
    "id": "neue-welten-2027-01-02-1930",
    "company": "Hamburg Ballett",
    "city": "Hamburg",
    "venue": "Staatsoper, Großes Haus",
    "title": "NEUE WELTEN",
    "date": "2027-01-02",
    "time": "19:30",
    "datetime": "2027-01-02T19:30:00",
    "ticketUrl": "https://webshop.staatsoper-hamburg.de/webshop/webticket/shop?event=11157",
    "officialUrl": "https://hamburgballett.die-hamburgische-staatsoper.de/de/programm/ballett/1905-neue-welten"
  },
  {
    "id": "ballettinsider-innen-ballettabend-neue-welten-2027-01-06-1845",
    "company": "Hamburg Ballett",
    "city": "Hamburg",
    "venue": "Staatsoper, Gästezimmer",
    "title": "BallettInsider:innen – Ballettabend NEUE WELTEN",
    "date": "2027-01-06",
    "time": "18:45",
    "datetime": "2027-01-06T18:45:00",
    "ticketUrl": null,
    "officialUrl": "https://hamburgballett.die-hamburgische-staatsoper.de/de/programm/ballett/3054-ballettinsider-innen"
  },
  {
    "id": "neue-welten-2027-01-06-1930",
    "company": "Hamburg Ballett",
    "city": "Hamburg",
    "venue": "Staatsoper, Großes Haus",
    "title": "NEUE WELTEN",
    "date": "2027-01-06",
    "time": "19:30",
    "datetime": "2027-01-06T19:30:00",
    "ticketUrl": "https://webshop.staatsoper-hamburg.de/webshop/webticket/shop?event=11158",
    "officialUrl": "https://hamburgballett.die-hamburgische-staatsoper.de/de/programm/ballett/1905-neue-welten"
  },
  {
    "id": "tanz-fur-mich-2027-01-07-1900",
    "company": "Hamburg Ballett",
    "city": "Hamburg",
    "venue": "Ballettzentrum Hamburg – John Neumeier",
    "title": "Tanz für mich",
    "date": "2027-01-07",
    "time": "19:00",
    "datetime": "2027-01-07T19:00:00",
    "ticketUrl": null,
    "officialUrl": "https://hamburgballett.die-hamburgische-staatsoper.de/de/programm/ballett/3047-tanz-fuer-mich"
  },
  {
    "id": "romantic-evolution-s-2027-01-08-1900",
    "company": "Hamburg Ballett",
    "city": "Hamburg",
    "venue": "Staatsoper, Großes Haus",
    "title": "ROMANTIC EVOLUTION/S",
    "date": "2027-01-08",
    "time": "19:00",
    "datetime": "2027-01-08T19:00:00",
    "ticketUrl": "https://webshop.staatsoper-hamburg.de/webshop/webticket/shop?event=11089",
    "officialUrl": "https://hamburgballett.die-hamburgische-staatsoper.de/de/programm/ballett/2147484877-romantic-evolution-s"
  },
  {
    "id": "romantic-evolution-s-2027-01-09-1900",
    "company": "Hamburg Ballett",
    "city": "Hamburg",
    "venue": "Staatsoper, Großes Haus",
    "title": "ROMANTIC EVOLUTION/S",
    "date": "2027-01-09",
    "time": "19:00",
    "datetime": "2027-01-09T19:00:00",
    "ticketUrl": "https://webshop.staatsoper-hamburg.de/webshop/webticket/shop?event=11094",
    "officialUrl": "https://hamburgballett.die-hamburgische-staatsoper.de/de/programm/ballett/2147484877-romantic-evolution-s"
  },
  {
    "id": "romantic-evolution-s-2027-01-17-1400",
    "company": "Hamburg Ballett",
    "city": "Hamburg",
    "venue": "Staatsoper, Großes Haus",
    "title": "ROMANTIC EVOLUTION/S",
    "date": "2027-01-17",
    "time": "14:00",
    "datetime": "2027-01-17T14:00:00",
    "ticketUrl": "https://webshop.staatsoper-hamburg.de/webshop/webticket/shop?event=11091",
    "officialUrl": "https://hamburgballett.die-hamburgische-staatsoper.de/de/programm/ballett/2147484877-romantic-evolution-s"
  },
  {
    "id": "romantic-evolution-s-2027-01-17-1900",
    "company": "Hamburg Ballett",
    "city": "Hamburg",
    "venue": "Staatsoper, Großes Haus",
    "title": "ROMANTIC EVOLUTION/S",
    "date": "2027-01-17",
    "time": "19:00",
    "datetime": "2027-01-17T19:00:00",
    "ticketUrl": "https://webshop.staatsoper-hamburg.de/webshop/webticket/shop?event=11090",
    "officialUrl": "https://hamburgballett.die-hamburgische-staatsoper.de/de/programm/ballett/2147484877-romantic-evolution-s"
  },
  {
    "id": "romantic-evolution-s-2027-01-18-1900",
    "company": "Hamburg Ballett",
    "city": "Hamburg",
    "venue": "Staatsoper, Großes Haus",
    "title": "ROMANTIC EVOLUTION/S",
    "date": "2027-01-18",
    "time": "19:00",
    "datetime": "2027-01-18T19:00:00",
    "ticketUrl": "https://webshop.staatsoper-hamburg.de/webshop/webticket/shop?event=11092",
    "officialUrl": "https://hamburgballett.die-hamburgische-staatsoper.de/de/programm/ballett/2147484877-romantic-evolution-s"
  },
  {
    "id": "patenklassen-ballett-die-mowe-2027-01-20-0930",
    "company": "Hamburg Ballett",
    "city": "Hamburg",
    "venue": "Staatsoper, Großes Haus",
    "title": "Patenklassen Ballett – Die Möwe",
    "date": "2027-01-20",
    "time": "09:30",
    "datetime": "2027-01-20T09:30:00",
    "ticketUrl": null,
    "officialUrl": "https://hamburgballett.die-hamburgische-staatsoper.de/de/programm/ballett/3050-patenklassen-ballett"
  },
  {
    "id": "die-mowe-2027-01-20-1930",
    "company": "Hamburg Ballett",
    "city": "Hamburg",
    "venue": "Staatsoper, Großes Haus",
    "title": "Die Möwe",
    "date": "2027-01-20",
    "time": "19:30",
    "datetime": "2027-01-20T19:30:00",
    "ticketUrl": "https://webshop.staatsoper-hamburg.de/webshop/webticket/shop?event=11149",
    "officialUrl": "https://hamburgballett.die-hamburgische-staatsoper.de/de/programm/ballett/485-die-moewe"
  },
  {
    "id": "die-mowe-2027-01-23-1930",
    "company": "Hamburg Ballett",
    "city": "Hamburg",
    "venue": "Staatsoper, Großes Haus",
    "title": "Die Möwe",
    "date": "2027-01-23",
    "time": "19:30",
    "datetime": "2027-01-23T19:30:00",
    "ticketUrl": "https://webshop.staatsoper-hamburg.de/webshop/webticket/shop?event=11150",
    "officialUrl": "https://hamburgballett.die-hamburgische-staatsoper.de/de/programm/ballett/485-die-moewe"
  },
  {
    "id": "die-mowe-2027-01-26-1930",
    "company": "Hamburg Ballett",
    "city": "Hamburg",
    "venue": "Staatsoper, Großes Haus",
    "title": "Die Möwe",
    "date": "2027-01-26",
    "time": "19:30",
    "datetime": "2027-01-26T19:30:00",
    "ticketUrl": "https://webshop.staatsoper-hamburg.de/webshop/webticket/shop?event=11151",
    "officialUrl": "https://hamburgballett.die-hamburgische-staatsoper.de/de/programm/ballett/485-die-moewe"
  },
  {
    "id": "ballett-werkstatt-2027-01-31-1100",
    "company": "Hamburg Ballett",
    "city": "Hamburg",
    "venue": "Staatsoper, Großes Haus",
    "title": "Ballett-Werkstatt",
    "date": "2027-01-31",
    "time": "11:00",
    "datetime": "2027-01-31T11:00:00",
    "ticketUrl": "https://webshop.staatsoper-hamburg.de/webshop/webticket/shop?event=11284",
    "officialUrl": "https://hamburgballett.die-hamburgische-staatsoper.de/de/programm/ballett/168-ballett-werkstatt"
  },
  {
    "id": "die-mowe-2027-01-31-1700",
    "company": "Hamburg Ballett",
    "city": "Hamburg",
    "venue": "Staatsoper, Großes Haus",
    "title": "Die Möwe",
    "date": "2027-01-31",
    "time": "17:00",
    "datetime": "2027-01-31T17:00:00",
    "ticketUrl": "https://webshop.staatsoper-hamburg.de/webshop/webticket/shop?event=11152",
    "officialUrl": "https://hamburgballett.die-hamburgische-staatsoper.de/de/programm/ballett/485-die-moewe"
  },
  {
    "id": "tanz-fur-mich-2027-02-04-1900",
    "company": "Hamburg Ballett",
    "city": "Hamburg",
    "venue": "Ballettzentrum Hamburg – John Neumeier",
    "title": "Tanz für mich",
    "date": "2027-02-04",
    "time": "19:00",
    "datetime": "2027-02-04T19:00:00",
    "ticketUrl": null,
    "officialUrl": "https://hamburgballett.die-hamburgische-staatsoper.de/de/programm/ballett/3047-tanz-fuer-mich"
  },
  {
    "id": "patenklassen-ballett-fast-forward-2027-02-12-0930",
    "company": "Hamburg Ballett",
    "city": "Hamburg",
    "venue": "Staatsoper, Großes Haus",
    "title": "Patenklassen Ballett – FAST FORWARD",
    "date": "2027-02-12",
    "time": "09:30",
    "datetime": "2027-02-12T09:30:00",
    "ticketUrl": null,
    "officialUrl": "https://hamburgballett.die-hamburgische-staatsoper.de/de/programm/ballett/3050-patenklassen-ballett"
  },
  {
    "id": "fast-forward-2027-02-14-1800",
    "company": "Hamburg Ballett",
    "city": "Hamburg",
    "venue": "Staatsoper, Großes Haus",
    "title": "FAST FORWARD",
    "date": "2027-02-14",
    "time": "18:00",
    "datetime": "2027-02-14T18:00:00",
    "ticketUrl": "https://webshop.staatsoper-hamburg.de/webshop/webticket/shop?event=11099",
    "officialUrl": "https://hamburgballett.die-hamburgische-staatsoper.de/de/programm/ballett/3124-fast-forward"
  },
  {
    "id": "tanz-fur-mich-2027-02-18-1900",
    "company": "Hamburg Ballett",
    "city": "Hamburg",
    "venue": "Ballettzentrum Hamburg – John Neumeier",
    "title": "Tanz für mich",
    "date": "2027-02-18",
    "time": "19:00",
    "datetime": "2027-02-18T19:00:00",
    "ticketUrl": null,
    "officialUrl": "https://hamburgballett.die-hamburgische-staatsoper.de/de/programm/ballett/3048-tanz-fuer-mich"
  },
  {
    "id": "eintauchen-ins-ballettzentrum-2027-02-20-1000",
    "company": "Hamburg Ballett",
    "city": "Hamburg",
    "venue": "Ballettzentrum Hamburg – John Neumeier",
    "title": "Eintauchen ins Ballettzentrum",
    "date": "2027-02-20",
    "time": "10:00",
    "datetime": "2027-02-20T10:00:00",
    "ticketUrl": null,
    "officialUrl": "https://hamburgballett.die-hamburgische-staatsoper.de/de/programm/ballett/3146-eintauchen-ins-ballettzentrum"
  },
  {
    "id": "fast-forward-2027-02-20-1930",
    "company": "Hamburg Ballett",
    "city": "Hamburg",
    "venue": "Staatsoper, Großes Haus",
    "title": "FAST FORWARD",
    "date": "2027-02-20",
    "time": "19:30",
    "datetime": "2027-02-20T19:30:00",
    "ticketUrl": "https://webshop.staatsoper-hamburg.de/webshop/webticket/shop?event=11102",
    "officialUrl": "https://hamburgballett.die-hamburgische-staatsoper.de/de/programm/ballett/3124-fast-forward"
  },
  {
    "id": "werkstatt-der-kreativitat-xvii-programm-i-2027-02-22-1930",
    "company": "Hamburg Ballett",
    "city": "Hamburg",
    "venue": "Ernst Deutsch Theater",
    "title": "Werkstatt der Kreativität XVII – Programm I",
    "date": "2027-02-22",
    "time": "19:30",
    "datetime": "2027-02-22T19:30:00",
    "ticketUrl": null,
    "officialUrl": "https://hamburgballett.die-hamburgische-staatsoper.de/de/programm/ballett/2147484995-werkstatt-der-kreativitaet-xvii"
  },
  {
    "id": "werkstatt-der-kreativitat-xvii-programm-i-2027-02-23-1930",
    "company": "Hamburg Ballett",
    "city": "Hamburg",
    "venue": "Ernst Deutsch Theater",
    "title": "Werkstatt der Kreativität XVII – Programm I",
    "date": "2027-02-23",
    "time": "19:30",
    "datetime": "2027-02-23T19:30:00",
    "ticketUrl": null,
    "officialUrl": "https://hamburgballett.die-hamburgische-staatsoper.de/de/programm/ballett/2147484995-werkstatt-der-kreativitaet-xvii"
  },
  {
    "id": "fast-forward-2027-02-24-1930",
    "company": "Hamburg Ballett",
    "city": "Hamburg",
    "venue": "Staatsoper, Großes Haus",
    "title": "FAST FORWARD",
    "date": "2027-02-24",
    "time": "19:30",
    "datetime": "2027-02-24T19:30:00",
    "ticketUrl": "https://webshop.staatsoper-hamburg.de/webshop/webticket/shop?event=11100",
    "officialUrl": "https://hamburgballett.die-hamburgische-staatsoper.de/de/programm/ballett/3124-fast-forward"
  },
  {
    "id": "werkstatt-der-kreativitat-xvii-programm-i-2027-02-24-1930",
    "company": "Hamburg Ballett",
    "city": "Hamburg",
    "venue": "Ernst Deutsch Theater",
    "title": "Werkstatt der Kreativität XVII – Programm I",
    "date": "2027-02-24",
    "time": "19:30",
    "datetime": "2027-02-24T19:30:00",
    "ticketUrl": null,
    "officialUrl": "https://hamburgballett.die-hamburgische-staatsoper.de/de/programm/ballett/2147484995-werkstatt-der-kreativitaet-xvii"
  },
  {
    "id": "fast-forward-2027-02-26-1930",
    "company": "Hamburg Ballett",
    "city": "Hamburg",
    "venue": "Staatsoper, Großes Haus",
    "title": "FAST FORWARD",
    "date": "2027-02-26",
    "time": "19:30",
    "datetime": "2027-02-26T19:30:00",
    "ticketUrl": "https://webshop.staatsoper-hamburg.de/webshop/webticket/shop?event=11101",
    "officialUrl": "https://hamburgballett.die-hamburgische-staatsoper.de/de/programm/ballett/3124-fast-forward"
  },
  {
    "id": "werkstatt-der-kreativitat-xvii-programm-ii-2027-02-26-1930",
    "company": "Hamburg Ballett",
    "city": "Hamburg",
    "venue": "Ernst Deutsch Theater",
    "title": "Werkstatt der Kreativität XVII – Programm II",
    "date": "2027-02-26",
    "time": "19:30",
    "datetime": "2027-02-26T19:30:00",
    "ticketUrl": null,
    "officialUrl": "https://hamburgballett.die-hamburgische-staatsoper.de/de/programm/ballett/2147484995-werkstatt-der-kreativitaet-xvii"
  },
  {
    "id": "werkstatt-der-kreativitat-xvii-programm-ii-2027-02-27-1930",
    "company": "Hamburg Ballett",
    "city": "Hamburg",
    "venue": "Ernst Deutsch Theater",
    "title": "Werkstatt der Kreativität XVII – Programm II",
    "date": "2027-02-27",
    "time": "19:30",
    "datetime": "2027-02-27T19:30:00",
    "ticketUrl": null,
    "officialUrl": "https://hamburgballett.die-hamburgische-staatsoper.de/de/programm/ballett/2147484995-werkstatt-der-kreativitaet-xvii"
  },
  {
    "id": "werkstatt-der-kreativitat-xvii-programm-ii-2027-02-28-1930",
    "company": "Hamburg Ballett",
    "city": "Hamburg",
    "venue": "Ernst Deutsch Theater",
    "title": "Werkstatt der Kreativität XVII – Programm II",
    "date": "2027-02-28",
    "time": "19:30",
    "datetime": "2027-02-28T19:30:00",
    "ticketUrl": null,
    "officialUrl": "https://hamburgballett.die-hamburgische-staatsoper.de/de/programm/ballett/2147484995-werkstatt-der-kreativitaet-xvii"
  },
  {
    "id": "tanz-fur-mich-2027-03-04-1900",
    "company": "Hamburg Ballett",
    "city": "Hamburg",
    "venue": "Ballettzentrum Hamburg – John Neumeier",
    "title": "Tanz für mich",
    "date": "2027-03-04",
    "time": "19:00",
    "datetime": "2027-03-04T19:00:00",
    "ticketUrl": null,
    "officialUrl": "https://hamburgballett.die-hamburgische-staatsoper.de/de/programm/ballett/3047-tanz-fuer-mich"
  },
  {
    "id": "sneak-klub-generalprobe-mittsu-2027-03-12-1700",
    "company": "Hamburg Ballett",
    "city": "Hamburg",
    "venue": "Staatsoper, Großes Haus",
    "title": "Sneak Klub – Generalprobe: MITTSU",
    "date": "2027-03-12",
    "time": "17:00",
    "datetime": "2027-03-12T17:00:00",
    "ticketUrl": null,
    "officialUrl": "https://hamburgballett.die-hamburgische-staatsoper.de/de/programm/ballett/2147484910-sneak-klub"
  },
  {
    "id": "mittsu-virginia-woolf-2027-03-13-1800",
    "company": "Hamburg Ballett",
    "city": "Hamburg",
    "venue": "Staatsoper, Großes Haus",
    "title": "MITTSU: Virginia Woolf",
    "date": "2027-03-13",
    "time": "18:00",
    "datetime": "2027-03-13T18:00:00",
    "ticketUrl": "https://webshop.staatsoper-hamburg.de/webshop/webticket/shop?event=11141",
    "officialUrl": "https://hamburgballett.die-hamburgische-staatsoper.de/de/programm/ballett/1974-mittsu-virginia-woolf"
  },
  {
    "id": "mittsu-virginia-woolf-2027-03-14-1800",
    "company": "Hamburg Ballett",
    "city": "Hamburg",
    "venue": "Staatsoper, Großes Haus",
    "title": "MITTSU: Virginia Woolf",
    "date": "2027-03-14",
    "time": "18:00",
    "datetime": "2027-03-14T18:00:00",
    "ticketUrl": "https://webshop.staatsoper-hamburg.de/webshop/webticket/shop?event=11142",
    "officialUrl": "https://hamburgballett.die-hamburgische-staatsoper.de/de/programm/ballett/1974-mittsu-virginia-woolf"
  },
  {
    "id": "matthaus-passion-2027-03-18-1830",
    "company": "Hamburg Ballett",
    "city": "Hamburg",
    "venue": "Aufführungsort wird noch bekannt gegeben",
    "title": "Matthäus-Passion",
    "date": "2027-03-18",
    "time": "18:30",
    "datetime": "2027-03-18T18:30:00",
    "ticketUrl": null,
    "officialUrl": "https://hamburgballett.die-hamburgische-staatsoper.de/de/programm/ballett/174-matthaeus-passion"
  },
  {
    "id": "matthaus-passion-2027-03-19-1830",
    "company": "Hamburg Ballett",
    "city": "Hamburg",
    "venue": "Aufführungsort wird noch bekannt gegeben",
    "title": "Matthäus-Passion",
    "date": "2027-03-19",
    "time": "18:30",
    "datetime": "2027-03-19T18:30:00",
    "ticketUrl": null,
    "officialUrl": "https://hamburgballett.die-hamburgische-staatsoper.de/de/programm/ballett/174-matthaeus-passion"
  },
  {
    "id": "wunderland-2027-03-20-1930",
    "company": "Hamburg Ballett",
    "city": "Hamburg",
    "venue": "Staatsoper, Großes Haus",
    "title": "Wunderland",
    "date": "2027-03-20",
    "time": "19:30",
    "datetime": "2027-03-20T19:30:00",
    "ticketUrl": "https://webshop.staatsoper-hamburg.de/webshop/webticket/shop?event=11216",
    "officialUrl": "https://hamburgballett.die-hamburgische-staatsoper.de/de/programm/ballett/1911-wunderland"
  },
  {
    "id": "mittsu-virginia-woolf-2027-03-21-1700",
    "company": "Hamburg Ballett",
    "city": "Hamburg",
    "venue": "Staatsoper, Großes Haus",
    "title": "MITTSU: Virginia Woolf",
    "date": "2027-03-21",
    "time": "17:00",
    "datetime": "2027-03-21T17:00:00",
    "ticketUrl": "https://webshop.staatsoper-hamburg.de/webshop/webticket/shop?event=11144",
    "officialUrl": "https://hamburgballett.die-hamburgische-staatsoper.de/de/programm/ballett/1974-mittsu-virginia-woolf"
  },
  {
    "id": "scirocco-2027-03-23-1930",
    "company": "Hamburg Ballett",
    "city": "Hamburg",
    "venue": "Staatsoper, Großes Haus",
    "title": "Scirocco",
    "date": "2027-03-23",
    "time": "19:30",
    "datetime": "2027-03-23T19:30:00",
    "ticketUrl": "https://webshop.staatsoper-hamburg.de/webshop/webticket/shop?event=11245",
    "officialUrl": "https://hamburgballett.die-hamburgische-staatsoper.de/de/programm/ballett/1970-scirocco"
  },
  {
    "id": "scirocco-2027-03-24-1930",
    "company": "Hamburg Ballett",
    "city": "Hamburg",
    "venue": "Staatsoper, Großes Haus",
    "title": "Scirocco",
    "date": "2027-03-24",
    "time": "19:30",
    "datetime": "2027-03-24T19:30:00",
    "ticketUrl": "https://webshop.staatsoper-hamburg.de/webshop/webticket/shop?event=11246",
    "officialUrl": "https://hamburgballett.die-hamburgische-staatsoper.de/de/programm/ballett/1970-scirocco"
  },
  {
    "id": "romantic-evolution-s-2027-03-25-1900",
    "company": "Hamburg Ballett",
    "city": "Hamburg",
    "venue": "Staatsoper, Großes Haus",
    "title": "ROMANTIC EVOLUTION/S",
    "date": "2027-03-25",
    "time": "19:00",
    "datetime": "2027-03-25T19:00:00",
    "ticketUrl": "https://webshop.staatsoper-hamburg.de/webshop/webticket/shop?event=11093",
    "officialUrl": "https://hamburgballett.die-hamburgische-staatsoper.de/de/programm/ballett/2147484877-romantic-evolution-s"
  },
  {
    "id": "a-cinderella-story-2027-03-26-1800",
    "company": "Hamburg Ballett",
    "city": "Hamburg",
    "venue": "Staatsoper, Großes Haus",
    "title": "A Cinderella Story",
    "date": "2027-03-26",
    "time": "18:00",
    "datetime": "2027-03-26T18:00:00",
    "ticketUrl": "https://webshop.staatsoper-hamburg.de/webshop/webticket/shop?event=11079",
    "officialUrl": "https://hamburgballett.die-hamburgische-staatsoper.de/de/programm/ballett/319-a-cinderella-story"
  },
  {
    "id": "neue-welten-2027-03-27-2000",
    "company": "Hamburg Ballett",
    "city": "Hamburg",
    "venue": "Staatsoper, Großes Haus",
    "title": "NEUE WELTEN",
    "date": "2027-03-27",
    "time": "20:00",
    "datetime": "2027-03-27T20:00:00",
    "ticketUrl": "https://webshop.staatsoper-hamburg.de/webshop/webticket/shop?event=11159",
    "officialUrl": "https://hamburgballett.die-hamburgische-staatsoper.de/de/programm/ballett/1905-neue-welten"
  },
  {
    "id": "die-mowe-2027-03-28-1800",
    "company": "Hamburg Ballett",
    "city": "Hamburg",
    "venue": "Staatsoper, Großes Haus",
    "title": "Die Möwe",
    "date": "2027-03-28",
    "time": "18:00",
    "datetime": "2027-03-28T18:00:00",
    "ticketUrl": "https://webshop.staatsoper-hamburg.de/webshop/webticket/shop?event=11153",
    "officialUrl": "https://hamburgballett.die-hamburgische-staatsoper.de/de/programm/ballett/485-die-moewe"
  },
  {
    "id": "nijinsky-gala-2027-03-29-1800",
    "company": "Hamburg Ballett",
    "city": "Hamburg",
    "venue": "Staatsoper, Großes Haus",
    "title": "Nijinsky-Gala",
    "date": "2027-03-29",
    "time": "18:00",
    "datetime": "2027-03-29T18:00:00",
    "ticketUrl": "https://webshop.staatsoper-hamburg.de/webshop/webticket/shop?event=11231",
    "officialUrl": "https://hamburgballett.die-hamburgische-staatsoper.de/de/programm/ballett/206-nijinsky-gala"
  },
  {
    "id": "tanz-fur-mich-2027-04-01-1900",
    "company": "Hamburg Ballett",
    "city": "Hamburg",
    "venue": "Ballettzentrum Hamburg – John Neumeier",
    "title": "Tanz für mich",
    "date": "2027-04-01",
    "time": "19:00",
    "datetime": "2027-04-01T19:00:00",
    "ticketUrl": null,
    "officialUrl": "https://hamburgballett.die-hamburgische-staatsoper.de/de/programm/ballett/3047-tanz-fuer-mich"
  },
  {
    "id": "mittsu-virginia-woolf-2027-04-03-1930",
    "company": "Hamburg Ballett",
    "city": "Hamburg",
    "venue": "Staatsoper, Großes Haus",
    "title": "MITTSU: Virginia Woolf",
    "date": "2027-04-03",
    "time": "19:30",
    "datetime": "2027-04-03T19:30:00",
    "ticketUrl": "https://webshop.staatsoper-hamburg.de/webshop/webticket/shop?event=11145",
    "officialUrl": "https://hamburgballett.die-hamburgische-staatsoper.de/de/programm/ballett/1974-mittsu-virginia-woolf"
  },
  {
    "id": "mittsu-virginia-woolf-2027-04-05-1930",
    "company": "Hamburg Ballett",
    "city": "Hamburg",
    "venue": "Staatsoper, Großes Haus",
    "title": "MITTSU: Virginia Woolf",
    "date": "2027-04-05",
    "time": "19:30",
    "datetime": "2027-04-05T19:30:00",
    "ticketUrl": "https://webshop.staatsoper-hamburg.de/webshop/webticket/shop?event=11146",
    "officialUrl": "https://hamburgballett.die-hamburgische-staatsoper.de/de/programm/ballett/1974-mittsu-virginia-woolf"
  },
  {
    "id": "mittsu-virginia-woolf-2027-04-08-1930",
    "company": "Hamburg Ballett",
    "city": "Hamburg",
    "venue": "Staatsoper, Großes Haus",
    "title": "MITTSU: Virginia Woolf",
    "date": "2027-04-08",
    "time": "19:30",
    "datetime": "2027-04-08T19:30:00",
    "ticketUrl": "https://webshop.staatsoper-hamburg.de/webshop/webticket/shop?event=11143",
    "officialUrl": "https://hamburgballett.die-hamburgische-staatsoper.de/de/programm/ballett/1974-mittsu-virginia-woolf"
  },
  {
    "id": "patenklassen-ballett-die-kleine-meerjungfrau-2027-04-09-0930",
    "company": "Hamburg Ballett",
    "city": "Hamburg",
    "venue": "Staatsoper, Großes Haus",
    "title": "Patenklassen Ballett – Die kleine Meerjungfrau",
    "date": "2027-04-09",
    "time": "09:30",
    "datetime": "2027-04-09T09:30:00",
    "ticketUrl": null,
    "officialUrl": "https://hamburgballett.die-hamburgische-staatsoper.de/de/programm/ballett/3050-patenklassen-ballett"
  },
  {
    "id": "die-kleine-meerjungfrau-2027-04-09-1930",
    "company": "Hamburg Ballett",
    "city": "Hamburg",
    "venue": "Staatsoper, Großes Haus",
    "title": "Die kleine Meerjungfrau",
    "date": "2027-04-09",
    "time": "19:30",
    "datetime": "2027-04-09T19:30:00",
    "ticketUrl": "https://webshop.staatsoper-hamburg.de/webshop/webticket/shop?event=11135",
    "officialUrl": "https://hamburgballett.die-hamburgische-staatsoper.de/de/programm/ballett/566-die-kleine-meerjungfrau"
  },
  {
    "id": "eintauchen-ins-ballettzentrum-2027-04-10-1000",
    "company": "Hamburg Ballett",
    "city": "Hamburg",
    "venue": "Ballettzentrum Hamburg – John Neumeier",
    "title": "Eintauchen ins Ballettzentrum",
    "date": "2027-04-10",
    "time": "10:00",
    "datetime": "2027-04-10T10:00:00",
    "ticketUrl": null,
    "officialUrl": "https://hamburgballett.die-hamburgische-staatsoper.de/de/programm/ballett/3146-eintauchen-ins-ballettzentrum"
  },
  {
    "id": "mittsu-virginia-woolf-2027-04-11-1400",
    "company": "Hamburg Ballett",
    "city": "Hamburg",
    "venue": "Staatsoper, Großes Haus",
    "title": "MITTSU: Virginia Woolf",
    "date": "2027-04-11",
    "time": "14:00",
    "datetime": "2027-04-11T14:00:00",
    "ticketUrl": "https://webshop.staatsoper-hamburg.de/webshop/webticket/shop?event=11148",
    "officialUrl": "https://hamburgballett.die-hamburgische-staatsoper.de/de/programm/ballett/1974-mittsu-virginia-woolf"
  },
  {
    "id": "mittsu-virginia-woolf-2027-04-11-1900",
    "company": "Hamburg Ballett",
    "city": "Hamburg",
    "venue": "Staatsoper, Großes Haus",
    "title": "MITTSU: Virginia Woolf",
    "date": "2027-04-11",
    "time": "19:00",
    "datetime": "2027-04-11T19:00:00",
    "ticketUrl": "https://webshop.staatsoper-hamburg.de/webshop/webticket/shop?event=11147",
    "officialUrl": "https://hamburgballett.die-hamburgische-staatsoper.de/de/programm/ballett/1974-mittsu-virginia-woolf"
  },
  {
    "id": "ballettinsider-innen-die-kleine-meerjungfrau-2027-04-14-1845",
    "company": "Hamburg Ballett",
    "city": "Hamburg",
    "venue": "Staatsoper, Gästezimmer",
    "title": "BallettInsider:innen – Die kleine Meerjungfrau",
    "date": "2027-04-14",
    "time": "18:45",
    "datetime": "2027-04-14T18:45:00",
    "ticketUrl": null,
    "officialUrl": "https://hamburgballett.die-hamburgische-staatsoper.de/de/programm/ballett/3054-ballettinsider-innen"
  },
  {
    "id": "die-kleine-meerjungfrau-2027-04-14-1930",
    "company": "Hamburg Ballett",
    "city": "Hamburg",
    "venue": "Staatsoper, Großes Haus",
    "title": "Die kleine Meerjungfrau",
    "date": "2027-04-14",
    "time": "19:30",
    "datetime": "2027-04-14T19:30:00",
    "ticketUrl": "https://webshop.staatsoper-hamburg.de/webshop/webticket/shop?event=11140",
    "officialUrl": "https://hamburgballett.die-hamburgische-staatsoper.de/de/programm/ballett/566-die-kleine-meerjungfrau"
  },
  {
    "id": "die-kleine-meerjungfrau-2027-04-16-1930",
    "company": "Hamburg Ballett",
    "city": "Hamburg",
    "venue": "Staatsoper, Großes Haus",
    "title": "Die kleine Meerjungfrau",
    "date": "2027-04-16",
    "time": "19:30",
    "datetime": "2027-04-16T19:30:00",
    "ticketUrl": "https://webshop.staatsoper-hamburg.de/webshop/webticket/shop?event=11136",
    "officialUrl": "https://hamburgballett.die-hamburgische-staatsoper.de/de/programm/ballett/566-die-kleine-meerjungfrau"
  },
  {
    "id": "die-kleine-meerjungfrau-2027-04-20-1930",
    "company": "Hamburg Ballett",
    "city": "Hamburg",
    "venue": "Staatsoper, Großes Haus",
    "title": "Die kleine Meerjungfrau",
    "date": "2027-04-20",
    "time": "19:30",
    "datetime": "2027-04-20T19:30:00",
    "ticketUrl": "https://webshop.staatsoper-hamburg.de/webshop/webticket/shop?event=11137",
    "officialUrl": "https://hamburgballett.die-hamburgische-staatsoper.de/de/programm/ballett/566-die-kleine-meerjungfrau"
  },
  {
    "id": "erste-schritte-2027-04-21-1900",
    "company": "Hamburg Ballett",
    "city": "Hamburg",
    "venue": "Staatsoper, Großes Haus",
    "title": "Erste Schritte",
    "date": "2027-04-21",
    "time": "19:00",
    "datetime": "2027-04-21T19:00:00",
    "ticketUrl": "https://webshop.staatsoper-hamburg.de/webshop/webticket/shop?event=11289",
    "officialUrl": "https://hamburgballett.die-hamburgische-staatsoper.de/de/programm/ballett/205-erste-schritte"
  },
  {
    "id": "die-kleine-meerjungfrau-2027-04-22-1930",
    "company": "Hamburg Ballett",
    "city": "Hamburg",
    "venue": "Staatsoper, Großes Haus",
    "title": "Die kleine Meerjungfrau",
    "date": "2027-04-22",
    "time": "19:30",
    "datetime": "2027-04-22T19:30:00",
    "ticketUrl": "https://webshop.staatsoper-hamburg.de/webshop/webticket/shop?event=11138",
    "officialUrl": "https://hamburgballett.die-hamburgische-staatsoper.de/de/programm/ballett/566-die-kleine-meerjungfrau"
  },
  {
    "id": "erste-schritte-2027-04-23-1200",
    "company": "Hamburg Ballett",
    "city": "Hamburg",
    "venue": "Staatsoper, Großes Haus",
    "title": "Erste Schritte",
    "date": "2027-04-23",
    "time": "12:00",
    "datetime": "2027-04-23T12:00:00",
    "ticketUrl": null,
    "officialUrl": "https://hamburgballett.die-hamburgische-staatsoper.de/de/programm/ballett/205-erste-schritte"
  }
]
